snowdrop/__init__.py
snowdrop/__main__.py
snowdrop/ast_renderer.py
snowdrop/base_renderer.py
snowdrop/block_token.py
snowdrop/block_tokenizer.py
snowdrop/cli.py
snowdrop/core_tokens.py
snowdrop/html_renderer.py
snowdrop/latex_renderer.py
snowdrop/latex_token.py
snowdrop/markdown_renderer.py
snowdrop/py.typed
snowdrop/span_token.py
snowdrop/span_tokenizer.py
snowdrop/token.py
snowdrop/utils.py
snowdrop/contrib/__init__.py
snowdrop/contrib/github_wiki.py
snowdrop/contrib/jira_renderer.py
snowdrop/contrib/mathjax.py
snowdrop/contrib/md2jira.py
snowdrop/contrib/pygments_renderer.py
snowdrop/contrib/scheme.py
snowdrop/contrib/toc_renderer.py
snowdrop/contrib/xwiki20_renderer.py
snowdrop-1.5.2.dist-info/LICENSE
snowdrop-1.5.2.dist-info/METADATA
snowdrop-1.5.2.dist-info/WHEEL
snowdrop-1.5.2.dist-info/entry_points.txt
snowdrop-1.5.2.dist-info/top_level.txt
snowdrop-1.5.2.dist-info/RECORD
